bottle_cassandra_driver.py
setup.py
bottle_cassandra_driver.egg-info/PKG-INFO
bottle_cassandra_driver.egg-info/SOURCES.txt
bottle_cassandra_driver.egg-info/dependency_links.txt
bottle_cassandra_driver.egg-info/not-zip-safe
bottle_cassandra_driver.egg-info/requires.txt
bottle_cassandra_driver.egg-info/top_level.txt