Metadata-Version: 1.1
Name: bottle-cassandra-driver
Version: 0.0.1
Summary: Cassandra Driver plugin for Bottle.
Home-page: http://github.com/jeffjirsa/bottle-cassandra-driver/
Author: Jeff Jirsa
Author-email: jeff@jeffjirsa.net
License: MIT
Platform: any
Classifier: Environment :: Web Environment
Classifier: Intended Audience :: Developers
Classifier: License :: OSI Approved :: MIT License
Classifier: Operating System :: OS Independent
Classifier: Programming Language :: Python
Classifier: Topic :: Internet :: WWW/HTTP :: Dynamic Content
Classifier: Topic :: Software Development :: Libraries :: Python Modules
